ni_measurement_plugin_sdk_service/__init__.py
ni_measurement_plugin_sdk_service/_annotations.py
ni_measurement_plugin_sdk_service/_configuration.py
ni_measurement_plugin_sdk_service/_datatypeinfo.py
ni_measurement_plugin_sdk_service/_dotenvpath.py
ni_measurement_plugin_sdk_service/_featuretoggles.py
ni_measurement_plugin_sdk_service/_internal/__init__.py
ni_measurement_plugin_sdk_service/_internal/discovery_client.py
ni_measurement_plugin_sdk_service/_internal/grpc_servicer.py
ni_measurement_plugin_sdk_service/_internal/parameter/__init__.py
ni_measurement_plugin_sdk_service/_internal/parameter/_get_type.py
ni_measurement_plugin_sdk_service/_internal/parameter/decoder.py
ni_measurement_plugin_sdk_service/_internal/parameter/encoder.py
ni_measurement_plugin_sdk_service/_internal/parameter/metadata.py
ni_measurement_plugin_sdk_service/_internal/parameter/serialization_descriptors.py
ni_measurement_plugin_sdk_service/_internal/service_manager.py
ni_measurement_plugin_sdk_service/discovery/__init__.py
ni_measurement_plugin_sdk_service/grpc/__init__.py
ni_measurement_plugin_sdk_service/grpc/channelpool.py
ni_measurement_plugin_sdk_service/grpc/loggers.py
ni_measurement_plugin_sdk_service/measurement/__init__.py
ni_measurement_plugin_sdk_service/measurement/client_support.py
ni_measurement_plugin_sdk_service/measurement/info.py
ni_measurement_plugin_sdk_service/measurement/service.py
ni_measurement_plugin_sdk_service/pin_map/__init__.py
ni_measurement_plugin_sdk_service/py.typed
ni_measurement_plugin_sdk_service/session_management/__init__.py
ni_measurement_plugin_sdk_service/session_management/_reservation.py
ni_measurement_plugin_sdk_service/session_management/_types.py
ni_measurement_plugin_sdk_service-3.1.0.dist-info/METADATA
ni_measurement_plugin_sdk_service-3.1.0.dist-info/WHEEL
ni_measurement_plugin_sdk_service-3.1.0.dist-info/RECORD
