Metadata-Version: 2.3
Name: ni_measurement_plugin_sdk_service
Version: 3.1.0
Summary: Measurement Plug-In Support for Python
License: MIT
Author: NI
Author-email: opensource@ni.com
Requires-Python: >=3.10,<4.0
Classifier: Development Status :: 5 - Production/Stable
Classifier: Intended Audience :: Developers
Classifier: Intended Audience :: Manufacturing
Classifier: Intended Audience :: Science/Research
Classifier: License :: OSI Approved :: MIT License
Classifier: Operating System :: Microsoft :: Windows
Classifier: Programming Language :: Python :: 3
Classifier: Programming Language :: Python :: 3.10
Classifier: Programming Language :: Python :: 3.11
Classifier: Programming Language :: Python :: 3.12
Classifier: Programming Language :: Python :: 3.13
Classifier: Programming Language :: Python :: Implementation :: CPython
Classifier: Topic :: Scientific/Engineering
Classifier: Topic :: System :: Hardware
Provides-Extra: drivers
Provides-Extra: nidaqmx
Provides-Extra: nidcpower
Provides-Extra: nidigital
Provides-Extra: nidmm
Provides-Extra: nifgen
Provides-Extra: niscope
Provides-Extra: niswitch
Requires-Dist: deprecation (>=2.1)
Requires-Dist: grpcio (>=1.49.1,<2.0.0)
Requires-Dist: ni-grpc-extensions (>=1.0.0,<2.0.0)
Requires-Dist: ni-measurementlink-discovery-v1-client (>=1.0.0,<2.0.0)
Requires-Dist: ni-measurementlink-measurement-v1-proto (>=1.0.0,<2.0.0)
Requires-Dist: ni-measurementlink-measurement-v2-proto (>=1.0.0,<2.0.0)
Requires-Dist: ni-measurementlink-pinmap-v1-client (>=1.0.0,<2.0.0)
Requires-Dist: ni-measurementlink-sessionmanagement-v1-client (>=1.0.0,<2.0.0)
Requires-Dist: ni-protobuf-types (>=1.0.0,<2.0.0)
Requires-Dist: nidaqmx[grpc] (>=0.8.0) ; extra == "drivers" or extra == "nidaqmx"
Requires-Dist: nidcpower[grpc] (>=1.4.4) ; extra == "drivers" or extra == "nidcpower"
Requires-Dist: nidigital[grpc] (>=1.4.4) ; extra == "drivers" or extra == "nidigital"
Requires-Dist: nidmm[grpc] (>=1.4.4) ; extra == "drivers" or extra == "nidmm"
Requires-Dist: nifgen[grpc] (>=1.4.4) ; extra == "drivers" or extra == "nifgen"
Requires-Dist: niscope[grpc] (>=1.4.4) ; extra == "drivers" or extra == "niscope"
Requires-Dist: niswitch[grpc] (>=1.4.4) ; extra == "drivers" or extra == "niswitch"
Requires-Dist: protobuf (>=4.21)
Requires-Dist: python-decouple (>=3.8)
Requires-Dist: pywin32 (>=303) ; sys_platform == "win32"
Project-URL: Repository, https://github.com/ni/measurement-plugin-python/
